hyperdb_py/HyperDB.py
hyperdb_py/__init__.py
hyperdb_py-0.1.2.dist-info/METADATA
hyperdb_py-0.1.2.dist-info/WHEEL
hyperdb_py-0.1.2.dist-info/licenses/LICENSE
hyperdb_py-0.1.2.dist-info/RECORD
