Metadata-Version: 2.1
Name: hyperdb_py
Version: 0.1.2
Summary: HyperDB Python Client
Project-URL: Homepage, https://github.com/AfaanBilal/hyperdb-py
Project-URL: Bug Tracker, https://github.com/AfaanBilal/hyperdb-py/issues
Project-URL: Source, https://github.com/AfaanBilal/hyperdb-py
Author-email: Afaan Bilal <afaanbilal@gmail.com>
License-File: LICENSE
Keywords: client,hyperdb,in-memory
Classifier: License :: OSI Approved :: MIT License
Classifier: Operating System :: OS Independent
Classifier: Programming Language :: Python :: 3
Requires-Python: >=3.7
